pep508_rs-0.3.0.dist-info/METADATA
pep508_rs-0.3.0.dist-info/WHEEL
pep508_rs/__init__.py
pep508_rs/pep508_rs.abi3.so
pep508_rs-0.3.0.dist-info/RECORD
