Metadata-Version: 2.3
Name: pep508_rs
Version: 0.3.0
Summary: A library for python dependency specifiers, better known as PEP 508
License: Apache-2.0 OR BSD-2-Clause
Project-URL: Source Code, https://github.com/konstin/pep508_rs
